bodo-2026.1.dist-info/RECORD
bodo-2026.1.dist-info/WHEEL
bodo-2026.1.dist-info/METADATA
bodo-2026.1.dist-info/licenses/LICENSE
bodo-2026.1.dist-info/licenses/LICENSES.third-party
bodo/compiler.py
bodo/pytest.ini
bodo/__init__.py
bodo/types.py
bodo/memory.cpython-314-darwin.so
bodo/memory_cpp.cpython-314-darwin.so
bodo/numba_compat.py
bodo/ext.cpython-314-darwin.so
bodo/pandas_compat.py
bodo/user_logging.py
bodo/runtests_caching.py
bodo/sql_plan_cache.py
bodo/runtests.py
bodo/decorators.py
bodo/hiframes/dataframe_indexing.py
bodo/hiframes/pd_index_ext.py
bodo/hiframes/pd_dataframe_ext.py
bodo/hiframes/timestamptz_ext.py
bodo/hiframes/series_impl.py
bodo/hiframes/pd_groupby_ext.py
bodo/hiframes/pd_series_ext.py
bodo/hiframes/time_ext.py
bodo/hiframes/series_dt_impl.py
bodo/hiframes/series_str_impl.py
bodo/hiframes/series_kernels.py
bodo/hiframes/__init__.py
bodo/hiframes/datetime_date_ext.py
bodo/hiframes/rolling.py
bodo/hiframes/boxing.py
bodo/hiframes/pd_multi_index_ext.py
bodo/hiframes/pd_categorical_ext.py
bodo/hiframes/datetime_timedelta_ext.py
bodo/hiframes/table.py
bodo/hiframes/series_indexing.py
bodo/hiframes/pd_timestamp_ext.py
bodo/hiframes/generic_pandas_coverage.py
bodo/hiframes/dataframe_impl.py
bodo/hiframes/pd_rolling_ext.py
bodo/hiframes/pd_offsets_ext.py
bodo/hiframes/split_impl.py
bodo/hiframes/datetime_datetime_ext.py
bodo/mpi4py/__init__.py
bodo/mpi4py/_vendored_mpi4py/__main__.pyi
bodo/mpi4py/_vendored_mpi4py/run.py
bodo/mpi4py/_vendored_mpi4py/__init__.pyi
bodo/mpi4py/_vendored_mpi4py/run.pyi
bodo/mpi4py/_vendored_mpi4py/__init__.py
bodo/mpi4py/_vendored_mpi4py/bench.py
bodo/mpi4py/_vendored_mpi4py/bench.pyi
bodo/mpi4py/_vendored_mpi4py/typing.pyi
bodo/mpi4py/_vendored_mpi4py/MPI.pyi
bodo/mpi4py/_vendored_mpi4py/py.typed
bodo/mpi4py/_vendored_mpi4py/MPI.cpython-314-darwin.so
bodo/mpi4py/_vendored_mpi4py/typing.py
bodo/mpi4py/_vendored_mpi4py/__main__.py
bodo/mpi4py/_vendored_mpi4py/futures/__main__.pyi
bodo/mpi4py/_vendored_mpi4py/futures/_base.py
bodo/mpi4py/_vendored_mpi4py/futures/server.py
bodo/mpi4py/_vendored_mpi4py/futures/__init__.pyi
