Metadata-Version: 2.2
Name: bodo
Version: 2026.1
Summary: High-Performance Python Compute Engine for Data and AI
Keywords: data,analytics,cluster
Author: Bodo.ai
Classifier: Development Status :: 5 - Production/Stable
Classifier: Intended Audience :: Developers
Classifier: Operating System :: POSIX :: Linux
Classifier: Operating System :: MacOS :: MacOS X
Classifier: Programming Language :: Python
Classifier: Programming Language :: Python :: 3.10
Classifier: Programming Language :: Python :: 3.11
Classifier: Programming Language :: Python :: 3.12
Classifier: Programming Language :: Python :: 3.13
Classifier: Programming Language :: Python :: 3.14
Classifier: Topic :: Software Development :: Compilers
Classifier: Topic :: System :: Distributed Computing
Project-URL: Homepage, https://bodo.ai
Project-URL: Documentation, https://docs.bodo.ai
Project-URL: Repository, https://github.com/bodo-ai/Bodo
Requires-Python: >=3.10
Requires-Dist: pyarrow<22.1,>=22.0
Requires-Dist: numba<0.64,>=0.62
Requires-Dist: pandas>=2.2
Requires-Dist: numpy>=1.24
Requires-Dist: fsspec>=2021.09
Requires-Dist: requests
Requires-Dist: cloudpickle>=3.0
Requires-Dist: psutil
Requires-Dist: impi-rt; sys_platform == "win32"
Provides-Extra: hdf5
Requires-Dist: h5py; extra == "hdf5"
Provides-Extra: sklearn
Requires-Dist: scikit-learn; extra == "sklearn"
Provides-Extra: plot
Requires-Dist: matplotlib; extra == "plot"
Provides-Extra: s3fs
Requires-Dist: s3fs>=2022.1.0; extra == "s3fs"
Provides-Extra: adlfs
Requires-Dist: adlfs>=2022.1.0; extra == "adlfs"
Provides-Extra: snowflake
Requires-Dist: snowflake-connector-python; extra == "snowflake"
Provides-Extra: mysql
Requires-Dist: sqlalchemy; extra == "mysql"
Requires-Dist: PyMySQL; extra == "mysql"
Provides-Extra: postgres
Requires-Dist: sqlalchemy; extra == "postgres"
Requires-Dist: psycopg2; extra == "postgres"
Provides-Extra: oracle
Requires-Dist: sqlalchemy; extra == "oracle"
Requires-Dist: cx-Oracle; extra == "oracle"
Requires-Dist: libaio; extra == "oracle"
Provides-Extra: iceberg
Requires-Dist: pyiceberg[glue]>=0.10; extra == "iceberg"
Provides-Extra: huggingface-hub
Requires-Dist: huggingface_hub; extra == "huggingface-hub"
Provides-Extra: openai
Requires-Dist: openai; extra == "openai"
